[
    {
        "name": "Маргарита",
        "desc": "пелате, кашкавал",
        "price": "240 ден.",
        "id": 1
    },
    {
        "name": "Капричиоза",
        "desc": "пелате, кашкавал, шунка, печурки",
        "price": "280 ден.",
        "id": 2
    },
    {
        "name": "Пеперони",
        "desc": "пелате, кашкавал, кулен, маслинки",
        "price": "300 ден.",
        "id": 3
    },
    {
        "name": "Терра пица",
        "desc": "пелате, кашкавал, шунка, врат, печурки",
        "price": "320 ден.",
        "id": 4
    },
    {
        "name": "Посна пица",
        "desc": "пелате, посен кашкавал, печурки, тиквички",
        "price": "240 ден.",
        "id": 5
    },
    {
        "name": "Пастрмајлија",
        "desc": "свинско/пилешко месо, јајца, сирење",
        "price": "260 ден.",
        "id": 6
    }
]
